{"type": "FeatureCollection", "features": [{"geometry": {"type": "Point", "coordinates": [-12.0564509, -76.9467371]}, "type": "Feature", "properties": {"name": "geo__baby"}}, {"geometry": {"type": "Point", "coordinates": [-15.8171767, -47.8966996]}, "type": "Feature", "properties": {"name": "geo__baby"}}, {"geometry": {"type": "Point", "coordinates": [-16.663987, -48.618707]}, "type": "Feature", "properties": {"name": "geo__baby"}}, {"geometry": {"type": "Point", "coordinates": [-166.5996925, 23.6913645]}, "type": "Feature", "properties": {"name": "geo__baby"}}, {"geometry": {"type": "Point", "coordinates": [-22.540419, -44.178385]}, "type": "Feature", "properties": {"name": "geo__baby"}}, {"geometry": {"type": "Point", "coordinates": [-22.540419, -44.178385]}, "type": "Feature", "properties": {"name": "geo__baby"}}, {"geometry": {"type": "Point", "coordinates": [-22.5404191, -44.178385]}, "type": "Feature", "properties": {"name": "geo__baby"}}, {"geometry": {"type": "Point", "coordinates": [-22.5404191, -44.178385]}, "type": "Feature", "properties": {"name": "geo__baby"}}, {"geometry": {"type": "Point", "coordinates": [-22.5404191, -44.178385]}, "type": "Feature", "properties": {"name": "geo__baby"}}, {"geometry": {"type": "Point", "coordinates": [-22.5404191, -44.178385]}, "type": "Feature", "properties": {"name": "geo__baby"}}, {"geometry": {"type": "Point", "coordinates": [-22.5404191, -44.178385]}, "type": "Feature", "properties": {"name": "geo__baby"}}, {"geometry": {"type": "Point", "coordinates": [-22.5404191, -44.178385]}, "type": "Feature", "properties": {"name": "geo__baby"}}, {"geometry": {"type": "Point", "coordinates": [-22.5404191, -44.178385]}, "type": "Feature", "properties": {"name": "geo__baby"}}, {"geometry": {"type": "Point", "coordinates": [-22.5404191, -44.178385]}, "type": "Feature", "properties": {"name": "geo__baby"}}, {"geometry": {"type": "Point", "coordinates": [-22.5404191, -44.178385]}, "type": "Feature", "properties": {"name": "geo__baby"}}, {"geometry": {"type": "Point", "coordinates": [-22.5404191, -44.178385]}, "type": "Feature", "properties": {"name": "geo__baby"}}, {"geometry": {"type": "Point", "coordinates": [-22.5404191, -44.178385]}, "type": "Feature", "properties": {"name": "geo__baby"}}, {"geometry": {"type": "Point", "coordinates": [-22.5404191, -44.178385]}, "type": "Feature", "properties": {"name": "geo__baby"}}, {"geometry": {"type": "Point", "coordinates": [-22.87228747, -43.79473303]}, "type": "Feature", "properties": {"name": "geo__baby"}}, {"geometry": {"type": "Point", "coordinates": [-23.579253, -46.60547171]}, "type": "Feature", "properties": {"name": "geo__baby"}}, {"geometry": {"type": "Point", "coordinates": [-23.6292272, -46.5548578]}, "type": "Feature", "properties": {"name": "geo__baby"}}, {"geometry": {"type": "Point", "coordinates": [-23.63236712, -46.60178488]}, "type": "Feature", "properties": {"name": "geo__baby"}}, {"geometry": {"type": "Point", "coordinates": [-24.0069167, -46.4039578]}, "type": "Feature", "properties": {"name": "geo__baby"}}, {"geometry": {"type": "Point", "coordinates": [-27.42873929, -48.46528415]}, "type": "Feature", "properties": {"name": "geo__baby"}}, {"geometry": {"type": "Point", "coordinates": [-28.00265142, 153.39376669]}, "type": "Feature", "properties": {"name": "geo__baby"}}, {"geometry": {"type": "Point", "coordinates": [-29.74254122, -52.40584756]}, "type": "Feature", "properties": {"name": "geo__baby"}}, {"geometry": {"type": "Point", "coordinates": [-3.761256, -38.579194]}, "type": "Feature", "properties": {"name": "geo__baby"}}, {"geometry": {"type": "Point", "coordinates": [-35.221264500000004, -5.7993179999999995]}, "type": "Feature", "properties": {"name": "geo__baby"}}, {"geometry": {"type": "Point", "coordinates": [-42.339304, -22.061913500000003]}, "type": "Feature", "properties": {"name": "geo__baby"}}, {"geometry": {"type": "Point", "coordinates": [-43.4415779, -22.9114217]}, "type": "Feature", "properties": {"name": "geo__baby"}}, {"geometry": {"type": "Point", "coordinates": [-46.5955455, -23.682803]}, "type": "Feature", "properties": {"name": "geo__baby"}}, {"geometry": {"type": "Point", "coordinates": [-46.5955455, -23.682803]}, "type": "Feature", "properties": {"name": "geo__baby"}}, {"geometry": {"type": "Point", "coordinates": [-47.796623000000004, -15.776253700000002]}, "type": "Feature", "properties": {"name": "geo__baby"}}, {"geometry": {"type": "Point", "coordinates": [-48.78799600000001, -21.54038235]}, "type": "Feature", "properties": {"name": "geo__baby"}}, {"geometry": {"type": "Point", "coordinates": [-49.28846045, -25.4952494]}, "type": "Feature", "properties": {"name": "geo__baby"}}, {"geometry": {"type": "Point", "coordinates": [-49.28846045, -25.4952494]}, "type": "Feature", "properties": {"name": "geo__baby"}}, {"geometry": {"type": "Point", "coordinates": [-53.184834, -14.239565299999999]}, "type": "Feature", "properties": {"name": "geo__baby"}}, {"geometry": {"type": "Point", "coordinates": [-53.184834, -14.239565299999999]}, "type": "Feature", "properties": {"name": "geo__baby"}}, {"geometry": {"type": "Point", "coordinates": [-6.1924031, 106.6729601]}, "type": "Feature", "properties": {"name": "geo__baby"}}, {"geometry": {"type": "Point", "coordinates": [-6.23494698, 106.99874159]}, "type": "Feature", "properties": {"name": "geo__baby"}}, {"geometry": {"type": "Point", "coordinates": [-7.3351645, 112.7704892]}, "type": "Feature", "properties": {"name": "geo__baby"}}, {"geometry": {"type": "Point", "coordinates": [-74.035124, 40.129243]}, "type": "Feature", "properties": {"name": "geo__baby"}}, {"geometry": {"type": "Point", "coordinates": [-77.0143985, 38.898467999999994]}, "type": "Feature", "properties": {"name": "geo__baby"}}, {"geometry": {"type": "Point", "coordinates": [-8.1022786, -34.9381051]}, "type": "Feature", "properties": {"name": "geo__baby"}}, {"geometry": {"type": "Point", "coordinates": [-80.6204545, 35.480154799999994]}, "type": "Feature", "properties": {"name": "geo__baby"}}, {"geometry": {"type": "Point", "coordinates": [-86.4055055, 35.8497165]}, "type": "Feature", "properties": {"name": "geo__baby"}}, {"geometry": {"type": "Point", "coordinates": [12.1534589, -86.2379885]}, "type": "Feature", "properties": {"name": "geo__baby"}}, {"geometry": {"type": "Point", "coordinates": [14.069732, 121.323548]}, "type": "Feature", "properties": {"name": "geo__baby"}}, {"geometry": {"type": "Point", "coordinates": [14.440326, 120.937457]}, "type": "Feature", "properties": {"name": "geo__baby"}}, {"geometry": {"type": "Point", "coordinates": [14.59155753, 120.97783887]}, "type": "Feature", "properties": {"name": "geo__baby"}}, {"geometry": {"type": "Point", "coordinates": [18.45023906, -66.51545577]}, "type": "Feature", "properties": {"name": "geo__baby"}}, {"geometry": {"type": "Point", "coordinates": [19.30406215, -99.12972841]}, "type": "Feature", "properties": {"name": "geo__baby"}}, {"geometry": {"type": "Point", "coordinates": [21.45241914, -158.00622781]}, "type": "Feature", "properties": {"name": "geo__baby"}}, {"geometry": {"type": "Point", "coordinates": [23.1715904, 79.932677]}, "type": "Feature", "properties": {"name": "geo__baby"}}, {"geometry": {"type": "Point", "coordinates": [24.95509125, -80.57300686]}, "type": "Feature", "properties": {"name": "geo__baby"}}, {"geometry": {"type": "Point", "coordinates": [25.75567061, -80.22267037]}, "type": "Feature", "properties": {"name": "geo__baby"}}, {"geometry": {"type": "Point", "coordinates": [25.763508, -100.2972893]}, "type": "Feature", "properties": {"name": "geo__baby"}}, {"geometry": {"type": "Point", "coordinates": [25.898217, -80.374641]}, "type": "Feature", "properties": {"name": "geo__baby"}}, {"geometry": {"type": "Point", "coordinates": [26.01083583, -80.25060559]}, "type": "Feature", "properties": {"name": "geo__baby"}}, {"geometry": {"type": "Point", "coordinates": [26.14284972, -81.76579267]}, "type": "Feature", "properties": {"name": "geo__baby"}}, {"geometry": {"type": "Point", "coordinates": [26.3373976, -98.1668715]}, "type": "Feature", "properties": {"name": "geo__baby"}}, {"geometry": {"type": "Point", "coordinates": [26.5175287, -78.6534257]}, "type": "Feature", "properties": {"name": "geo__baby"}}, {"geometry": {"type": "Point", "coordinates": [27.54601, -81.819954]}, "type": "Feature", "properties": {"name": "geo__baby"}}, {"geometry": {"type": "Point", "coordinates": [27.8622728, -82.3737039]}, "type": "Feature", "properties": {"name": "geo__baby"}}, {"geometry": {"type": "Point", "coordinates": [28.5198734, -81.4353938]}, "type": "Feature", "properties": {"name": "geo__baby"}}, {"geometry": {"type": "Point", "coordinates": [28.61498238, -81.1955583]}, "type": "Feature", "properties": {"name": "geo__baby"}}, {"geometry": {"type": "Point", "coordinates": [28.755275, -81.346154]}, "type": "Feature", "properties": {"name": "geo__baby"}}, {"geometry": {"type": "Point", "coordinates": [28.98981342, -96.64264301]}, "type": "Feature", "properties": {"name": "geo__baby"}}, {"geometry": {"type": "Point", "coordinates": [29.01721694, -95.42760624]}, "type": "Feature", "properties": {"name": "geo__baby"}}, {"geometry": {"type": "Point", "coordinates": [29.11935183, -82.08479582]}, "type": "Feature", "properties": {"name": "geo__baby"}}, {"geometry": {"type": "Point", "coordinates": [29.15402156, -82.05208468]}, "type": "Feature", "properties": {"name": "geo__baby"}}, {"geometry": {"type": "Point", "coordinates": [29.160797, -80.974814]}, "type": "Feature", "properties": {"name": "geo__baby"}}, {"geometry": {"type": "Point", "coordinates": [29.4373278, -98.5556493]}, "type": "Feature", "properties": {"name": "geo__baby"}}, {"geometry": {"type": "Point", "coordinates": [29.62362833, -95.39157167]}, "type": "Feature", "properties": {"name": "geo__baby"}}, {"geometry": {"type": "Point", "coordinates": [29.69056504, -97.64979045]}, "type": "Feature", "properties": {"name": "geo__baby"}}, {"geometry": {"type": "Point", "coordinates": [29.77262404, -94.85858208]}, "type": "Feature", "properties": {"name": "geo__baby"}}, {"geometry": {"type": "Point", "coordinates": [29.79420221, -95.73166304]}, "type": "Feature", "properties": {"name": "geo__baby"}}, {"geometry": {"type": "Point", "coordinates": [29.91171569, -95.41219153]}, "type": "Feature", "properties": {"name": "geo__baby"}}, {"geometry": {"type": "Point", "coordinates": [3.909706, -76.307838]}, "type": "Feature", "properties": {"name": "geo__baby"}}, {"geometry": {"type": "Point", "coordinates": [30.0361472, 31.2533297]}, "type": "Feature", "properties": {"name": "geo__baby"}}, {"geometry": {"type": "Point", "coordinates": [30.08446378, -91.94873122]}, "type": "Feature", "properties": {"name": "geo__baby"}}, {"geometry": {"type": "Point", "coordinates": [30.27241488, -81.43594055]}, "type": "Feature", "properties": {"name": "geo__baby"}}, {"geometry": {"type": "Point", "coordinates": [30.2859462, -90.92476408]}, "type": "Feature", "properties": {"name": "geo__baby"}}, {"geometry": {"type": "Point", "coordinates": [30.293178, -97.662746]}, "type": "Feature", "properties": {"name": "geo__baby"}}, {"geometry": {"type": "Point", "coordinates": [30.37571229, -86.28694681]}, "type": "Feature", "properties": {"name": "geo__baby"}}, {"geometry": {"type": "Point", "coordinates": [30.5789166, -81.8794311]}, "type": "Feature", "properties": {"name": "geo__baby"}}, {"geometry": {"type": "Point", "coordinates": [31.292345, -82.229599]}, "type": "Feature", "properties": {"name": "geo__baby"}}, {"geometry": {"type": "Point", "coordinates": [32.04098539, -81.15228639]}, "type": "Feature", "properties": {"name": "geo__baby"}}, {"geometry": {"type": "Point", "coordinates": [32.23538063, -80.99439145]}, "type": "Feature", "properties": {"name": "geo__baby"}}, {"geometry": {"type": "Point", "coordinates": [32.2397711, -110.9783899]}, "type": "Feature", "properties": {"name": "geo__baby"}}, {"geometry": {"type": "Point", "coordinates": [32.4120172, -84.9477816]}, "type": "Feature", "properties": {"name": "geo__baby"}}, {"geometry": {"type": "Point", "coordinates": [32.562611, -96.954482]}, "type": "Feature", "properties": {"name": "geo__baby"}}, {"geometry": {"type": "Point", "coordinates": [32.64653607, -96.80228256]}, "type": "Feature", "properties": {"name": "geo__baby"}}, {"geometry": {"type": "Point", "coordinates": [32.6839598, -97.43501499]}, "type": "Feature", "properties": {"name": "geo__baby"}}, {"geometry": {"type": "Point", "coordinates": [33.03324337, -96.99763587]}, "type": "Feature", "properties": {"name": "geo__baby"}}, {"geometry": {"type": "Point", "coordinates": [33.0485733, -112.01287237]}, "type": "Feature", "properties": {"name": "geo__baby"}}, {"geometry": {"type": "Point", "coordinates": [33.0485733, -112.01287237]}, "type": "Feature", "properties": {"name": "geo__baby"}}, {"geometry": {"type": "Point", "coordinates": [33.1372494, -95.59822909]}, "type": "Feature", "properties": {"name": "geo__baby"}}, {"geometry": {"type": "Point", "coordinates": [33.5296042, -81.7535189]}, "type": "Feature", "properties": {"name": "geo__baby"}}, {"geometry": {"type": "Point", "coordinates": [33.64237995, -83.95564839]}, "type": "Feature", "properties": {"name": "geo__baby"}}, {"geometry": {"type": "Point", "coordinates": [33.713241, -112.198986]}, "type": "Feature", "properties": {"name": "geo__baby"}}, {"geometry": {"type": "Point", "coordinates": [33.7600384, -118.2981139]}, "type": "Feature", "properties": {"name": "geo__baby"}}, {"geometry": {"type": "Point", "coordinates": [33.781023, -84.142156]}, "type": "Feature", "properties": {"name": "geo__baby"}}, {"geometry": {"type": "Point", "coordinates": [33.88045524, -84.24630225]}, "type": "Feature", "properties": {"name": "geo__baby"}}, {"geometry": {"type": "Point", "coordinates": [33.894423, -84.530452]}, "type": "Feature", "properties": {"name": "geo__baby"}}, {"geometry": {"type": "Point", "coordinates": [33.9076897, -84.5365913]}, "type": "Feature", "properties": {"name": "geo__baby"}}, {"geometry": {"type": "Point", "coordinates": [33.952842, -116.505376]}, "type": "Feature", "properties": {"name": "geo__baby"}}, {"geometry": {"type": "Point", "coordinates": [33.96735609, -118.32390732]}, "type": "Feature", "properties": {"name": "geo__baby"}}, {"geometry": {"type": "Point", "coordinates": [34.068564, -118.030969]}, "type": "Feature", "properties": {"name": "geo__baby"}}, {"geometry": {"type": "Point", "coordinates": [34.07563188, -117.90745085]}, "type": "Feature", "properties": {"name": "geo__baby"}}, {"geometry": {"type": "Point", "coordinates": [34.0945324, -82.5778471]}, "type": "Feature", "properties": {"name": "geo__baby"}}, {"geometry": {"type": "Point", "coordinates": [34.1776373, -118.5163239]}, "type": "Feature", "properties": {"name": "geo__baby"}}, {"geometry": {"type": "Point", "coordinates": [34.1776373, -118.5163239]}, "type": "Feature", "properties": {"name": "geo__baby"}}, {"geometry": {"type": "Point", "coordinates": [34.5272515, -82.6552726]}, "type": "Feature", "properties": {"name": "geo__baby"}}, {"geometry": {"type": "Point", "coordinates": [34.7344332, -78.82966337]}, "type": "Feature", "properties": {"name": "geo__baby"}}, {"geometry": {"type": "Point", "coordinates": [34.95739359, -85.72675966]}, "type": "Feature", "properties": {"name": "geo__baby"}}, {"geometry": {"type": "Point", "coordinates": [35.0167983, -89.7544233]}, "type": "Feature", "properties": {"name": "geo__baby"}}, {"geometry": {"type": "Point", "coordinates": [35.1279154, -77.09837345]}, "type": "Feature", "properties": {"name": "geo__baby"}}, {"geometry": {"type": "Point", "coordinates": [35.23549557, -78.95706444]}, "type": "Feature", "properties": {"name": "geo__baby"}}, {"geometry": {"type": "Point", "coordinates": [35.24322, 38.9566025]}, "type": "Feature", "properties": {"name": "geo__baby"}}, {"geometry": {"type": "Point", "coordinates": [35.3626351, -97.5656092]}, "type": "Feature", "properties": {"name": "geo__baby"}}, {"geometry": {"type": "Point", "coordinates": [35.88295246, -78.70279195]}, "type": "Feature", "properties": {"name": "geo__baby"}}, {"geometry": {"type": "Point", "coordinates": [35.9220196, -77.5741464]}, "type": "Feature", "properties": {"name": "geo__baby"}}, {"geometry": {"type": "Point", "coordinates": [36.1723516, -115.07834042]}, "type": "Feature", "properties": {"name": "geo__baby"}}, {"geometry": {"type": "Point", "coordinates": [36.23532877, -86.69739186]}, "type": "Feature", "properties": {"name": "geo__baby"}}, {"geometry": {"type": "Point", "coordinates": [36.30128243, -76.29882415]}, "type": "Feature", "properties": {"name": "geo__baby"}}, {"geometry": {"type": "Point", "coordinates": [36.61042097, -82.35913678]}, "type": "Feature", "properties": {"name": "geo__baby"}}, {"geometry": {"type": "Point", "coordinates": [37.07974976, -76.44675393]}, "type": "Feature", "properties": {"name": "geo__baby"}}, {"geometry": {"type": "Point", "coordinates": [37.72262794, -122.12990955]}, "type": "Feature", "properties": {"name": "geo__baby"}}, {"geometry": {"type": "Point", "coordinates": [37.9825, -121.203652]}, "type": "Feature", "properties": {"name": "geo__baby"}}, {"geometry": {"type": "Point", "coordinates": [38.088463, -0.73869]}, "type": "Feature", "properties": {"name": "geo__baby"}}, {"geometry": {"type": "Point", "coordinates": [38.098679, -85.854314]}, "type": "Feature", "properties": {"name": "geo__baby"}}, {"geometry": {"type": "Point", "coordinates": [38.2268806, -84.5305422]}, "type": "Feature", "properties": {"name": "geo__baby"}}, {"geometry": {"type": "Point", "coordinates": [38.346854, -75.57891]}, "type": "Feature", "properties": {"name": "geo__baby"}}, {"geometry": {"type": "Point", "coordinates": [38.34787461, -81.64495694]}, "type": "Feature", "properties": {"name": "geo__baby"}}, {"geometry": {"type": "Point", "coordinates": [38.499559, -76.798885]}, "type": "Feature", "properties": {"name": "geo__baby"}}, {"geometry": {"type": "Point", "coordinates": [38.57704261, -121.54544595]}, "type": "Feature", "properties": {"name": "geo__baby"}}, {"geometry": {"type": "Point", "coordinates": [38.86335614, -90.08147537]}, "type": "Feature", "properties": {"name": "geo__baby"}}, {"geometry": {"type": "Point", "coordinates": [39.009339, -95.742935]}, "type": "Feature", "properties": {"name": "geo__baby"}}, {"geometry": {"type": "Point", "coordinates": [39.01487525, -95.05255473]}, "type": "Feature", "properties": {"name": "geo__baby"}}, {"geometry": {"type": "Point", "coordinates": [39.28421603, -76.68246193]}, "type": "Feature", "properties": {"name": "geo__baby"}}, {"geometry": {"type": "Point", "coordinates": [39.28421603, -76.68246193]}, "type": "Feature", "properties": {"name": "geo__baby"}}, {"geometry": {"type": "Point", "coordinates": [39.548764, -119.774086]}, "type": "Feature", "properties": {"name": "geo__baby"}}, {"geometry": {"type": "Point", "coordinates": [40.02443172, -75.08179564]}, "type": "Feature", "properties": {"name": "geo__baby"}}, {"geometry": {"type": "Point", "coordinates": [40.02810128, -75.21825773]}, "type": "Feature", "properties": {"name": "geo__baby"}}, {"geometry": {"type": "Point", "coordinates": [40.0711597, -75.0796338]}, "type": "Feature", "properties": {"name": "geo__baby"}}, {"geometry": {"type": "Point", "coordinates": [40.09434617, -80.81006317]}, "type": "Feature", "properties": {"name": "geo__baby"}}, {"geometry": {"type": "Point", "coordinates": [40.1311023, -75.39925924]}, "type": "Feature", "properties": {"name": "geo__baby"}}, {"geometry": {"type": "Point", "coordinates": [40.15369425, -75.2200389]}, "type": "Feature", "properties": {"name": "geo__baby"}}, {"geometry": {"type": "Point", "coordinates": [40.27814982, -76.89226658]}, "type": "Feature", "properties": {"name": "geo__baby"}}, {"geometry": {"type": "Point", "coordinates": [40.27814982, -76.89226658]}, "type": "Feature", "properties": {"name": "geo__baby"}}, {"geometry": {"type": "Point", "coordinates": [40.44111111, -80.0]}, "type": "Feature", "properties": {"name": "geo__baby"}}, {"geometry": {"type": "Point", "coordinates": [40.63339453, -74.06131096]}, "type": "Feature", "properties": {"name": "geo__baby"}}, {"geometry": {"type": "Point", "coordinates": [40.6633321, -80.2353581]}, "type": "Feature", "properties": {"name": "geo__baby"}}, {"geometry": {"type": "Point", "coordinates": [40.675762, -80.246133]}, "type": "Feature", "properties": {"name": "geo__baby"}}, {"geometry": {"type": "Point", "coordinates": [40.70693878, -73.67479791]}, "type": "Feature", "properties": {"name": "geo__baby"}}, {"geometry": {"type": "Point", "coordinates": [40.7609899, -73.93962623]}, "type": "Feature", "properties": {"name": "geo__baby"}}, {"geometry": {"type": "Point", "coordinates": [40.91052794, -73.84691805]}, "type": "Feature", "properties": {"name": "geo__baby"}}, {"geometry": {"type": "Point", "coordinates": [41.30324086, -96.00974109]}, "type": "Feature", "properties": {"name": "geo__baby"}}, {"geometry": {"type": "Point", "coordinates": [41.30598, -73.962047]}, "type": "Feature", "properties": {"name": "geo__baby"}}, {"geometry": {"type": "Point", "coordinates": [41.396747, 2.166115]}, "type": "Feature", "properties": {"name": "geo__baby"}}, {"geometry": {"type": "Point", "coordinates": [41.434601, -82.693093]}, "type": "Feature", "properties": {"name": "geo__baby"}}, {"geometry": {"type": "Point", "coordinates": [41.5152269, -81.6031383]}, "type": "Feature", "properties": {"name": "geo__baby"}}, {"geometry": {"type": "Point", "coordinates": [41.525852, -72.8543694]}, "type": "Feature", "properties": {"name": "geo__baby"}}, {"geometry": {"type": "Point", "coordinates": [41.533931, -81.556325]}, "type": "Feature", "properties": {"name": "geo__baby"}}, {"geometry": {"type": "Point", "coordinates": [41.55230297, -88.05397148]}, "type": "Feature", "properties": {"name": "geo__baby"}}, {"geometry": {"type": "Point", "coordinates": [41.63865251, -83.63959169]}, "type": "Feature", "properties": {"name": "geo__baby"}}, {"geometry": {"type": "Point", "coordinates": [41.661513, -70.170546]}, "type": "Feature", "properties": {"name": "geo__baby"}}, {"geometry": {"type": "Point", "coordinates": [41.687423, -86.22721]}, "type": "Feature", "properties": {"name": "geo__baby"}}, {"geometry": {"type": "Point", "coordinates": [41.6915515, -86.2536858]}, "type": "Feature", "properties": {"name": "geo__baby"}}, {"geometry": {"type": "Point", "coordinates": [41.7399815, -81.2525498]}, "type": "Feature", "properties": {"name": "geo__baby"}}, {"geometry": {"type": "Point", "coordinates": [41.78971902, -74.74103889]}, "type": "Feature", "properties": {"name": "geo__baby"}}, {"geometry": {"type": "Point", "coordinates": [41.81983871, -71.43199923]}, "type": "Feature", "properties": {"name": "geo__baby"}}, {"geometry": {"type": "Point", "coordinates": [41.82930591, -87.67917284]}, "type": "Feature", "properties": {"name": "geo__baby"}}, {"geometry": {"type": "Point", "coordinates": [41.8509144, -87.7491262]}, "type": "Feature", "properties": {"name": "geo__baby"}}, {"geometry": {"type": "Point", "coordinates": [41.8509144, -87.7491262]}, "type": "Feature", "properties": {"name": "geo__baby"}}, {"geometry": {"type": "Point", "coordinates": [41.905795, -87.7584568]}, "type": "Feature", "properties": {"name": "geo__baby"}}, {"geometry": {"type": "Point", "coordinates": [41.97787599, -71.46978845]}, "type": "Feature", "properties": {"name": "geo__baby"}}, {"geometry": {"type": "Point", "coordinates": [42.135348, -72.530628]}, "type": "Feature", "properties": {"name": "geo__baby"}}, {"geometry": {"type": "Point", "coordinates": [42.164673, -85.2092228]}, "type": "Feature", "properties": {"name": "geo__baby"}}, {"geometry": {"type": "Point", "coordinates": [42.21388359, -83.48633872]}, "type": "Feature", "properties": {"name": "geo__baby"}}, {"geometry": {"type": "Point", "coordinates": [42.346291, -71.0976989]}, "type": "Feature", "properties": {"name": "geo__baby"}}, {"geometry": {"type": "Point", "coordinates": [42.40633983, -71.06059303]}, "type": "Feature", "properties": {"name": "geo__baby"}}, {"geometry": {"type": "Point", "coordinates": [42.448517, -83.170298]}, "type": "Feature", "properties": {"name": "geo__baby"}}, {"geometry": {"type": "Point", "coordinates": [42.53123671, -83.48428134]}, "type": "Feature", "properties": {"name": "geo__baby"}}, {"geometry": {"type": "Point", "coordinates": [42.56872533, -71.27908756]}, "type": "Feature", "properties": {"name": "geo__baby"}}, {"geometry": {"type": "Point", "coordinates": [42.62832762, -71.32165653]}, "type": "Feature", "properties": {"name": "geo__baby"}}, {"geometry": {"type": "Point", "coordinates": [42.655294, 21.180935]}, "type": "Feature", "properties": {"name": "geo__baby"}}, {"geometry": {"type": "Point", "coordinates": [42.71037259, -87.83427772]}, "type": "Feature", "properties": {"name": "geo__baby"}}, {"geometry": {"type": "Point", "coordinates": [42.72134679, -78.74456329]}, "type": "Feature", "properties": {"name": "geo__baby"}}, {"geometry": {"type": "Point", "coordinates": [42.804972, -83.732867]}, "type": "Feature", "properties": {"name": "geo__baby"}}, {"geometry": {"type": "Point", "coordinates": [42.936302, -76.554171]}, "type": "Feature", "properties": {"name": "geo__baby"}}, {"geometry": {"type": "Point", "coordinates": [43.19670792, -80.37969293]}, "type": "Feature", "properties": {"name": "geo__baby"}}, {"geometry": {"type": "Point", "coordinates": [43.2206482, -86.22741791]}, "type": "Feature", "properties": {"name": "geo__baby"}}, {"geometry": {"type": "Point", "coordinates": [45.495864, -93.599574]}, "type": "Feature", "properties": {"name": "geo__baby"}}, {"geometry": {"type": "Point", "coordinates": [45.516397, -122.938532]}, "type": "Feature", "properties": {"name": "geo__baby"}}, {"geometry": {"type": "Point", "coordinates": [49.1314621, -122.81197661]}, "type": "Feature", "properties": {"name": "geo__baby"}}, {"geometry": {"type": "Point", "coordinates": [5.619564, -0.299569]}, "type": "Feature", "properties": {"name": "geo__baby"}}, {"geometry": {"type": "Point", "coordinates": [5.61956467, -0.29957375]}, "type": "Feature", "properties": {"name": "geo__baby"}}, {"geometry": {"type": "Point", "coordinates": [5.6467815, -0.1552603]}, "type": "Feature", "properties": {"name": "geo__baby"}}, {"geometry": {"type": "Point", "coordinates": [50.7965609, 4.3211861]}, "type": "Feature", "properties": {"name": "geo__baby"}}, {"geometry": {"type": "Point", "coordinates": [8.7511099, -75.8952021]}, "type": "Feature", "properties": {"name": "geo__baby"}}, {"geometry": {"type": "Point", "coordinates": [9.045966, -79.423887]}, "type": "Feature", "properties": {"name": "geo__baby"}}]}
